[
    {
        "key": "ctrl+shift+down",
        "command": "workbench.action.terminal.focus",
        "when": "editorTextFocus"
    },
    {
        "key": "ctrl+shift+up",
        "command": "workbench.action.focusFirstEditorGroup",
        "when": "terminalFocus"
    },
    {
        "key": "ctrl+shift+right",
        "command": "workbench.action.nextEditor",
        "when": "editorTextFocus"
    },
    {
        "key": "ctrl+shift+left",
        "command": "workbench.action.previousEditor",
        "when": "editorTextFocus"
    }
]
